MaetInject-1.0.2.dist-info/DESCRIPTION.rst
MaetInject-1.0.2.dist-info/METADATA
MaetInject-1.0.2.dist-info/RECORD
MaetInject-1.0.2.dist-info/WHEEL
MaetInject-1.0.2.dist-info/entry_points.txt
MaetInject-1.0.2.dist-info/metadata.json
MaetInject-1.0.2.dist-info/top_level.txt
maetinject/__init__.py
maetinject/maetinject.py
