Metadata-Version: 2.0
Name: MaetInject
Version: 1.0.2
Summary: MIT
Home-page: https://github.com/antitree/meatinject
Author: antitree
Author-email: antitree@gmail.com
License: Creative Commons Attribution-Noncommercial-Share Alike license
Keywords: maetspin meat spin omg lol
Platform: UNKNOWN
Requires-Python: >=2.7, <4
